vuw_info/__init__.py
vuw_info/main.py
vuw_info-0.0.2.dist-info/METADATA
vuw_info-0.0.2.dist-info/WHEEL
vuw_info-0.0.2.dist-info/top_level.txt
vuw_info-0.0.2.dist-info/RECORD
